LICENSE
MANIFEST.in
README.md
requirements.txt
setup.cfg
setup.py
geather/__init__.py
geather/geather.py
geather.egg-info/PKG-INFO
geather.egg-info/SOURCES.txt
geather.egg-info/dependency_links.txt
geather.egg-info/not-zip-safe
geather.egg-info/top_level.txt